finepipe/.DS_Store
finepipe/__init__.py
finepipe/_config/__init__.py
finepipe/app/__init__.py
finepipe/batcktest/__init__.py
finepipe/constants/__init__.py
finepipe/data/__init__.py
finepipe/deeplearning/.DS_Store
finepipe/deeplearning/__init__.py
finepipe/deeplearning/component.py
finepipe/deeplearning/data.py
finepipe/deeplearning/lr_scheduler.py
finepipe/deeplearning/measures.py
finepipe/deeplearning/metrics.py
finepipe/deeplearning/module.py
finepipe/deeplearning/optimizer.py
finepipe/deeplearning/position.py
finepipe/deeplearning/trainer.py
finepipe/deeplearning/criterion/__init__.py
finepipe/deeplearning/criterion/ce.py
finepipe/deeplearning/criterion/criterion.py
finepipe/deeplearning/criterion/focal_mnp.py
finepipe/deeplearning/criterion/mnp.py
finepipe/deeplearning/criterion/mse.py
finepipe/deeplearning/cross_validation/__init__.py
finepipe/deeplearning/cross_validation/cross_validation.py
finepipe/deeplearning/cross_validation/fold.py
finepipe/deeplearning/cross_validation/sliding_window.py
finepipe/deeplearning/data_loader/__init__.py
finepipe/deeplearning/data_loader/data_loader.py
finepipe/deeplearning/data_loader/over_sampling.py
finepipe/deeplearning/data_loader/under_sampling.py
finepipe/deeplearning/dataset/__init__.py
finepipe/deeplearning/dataset/batsf_dataset.py
finepipe/deeplearning/dataset/bsf_dataset.py
finepipe/deeplearning/dataset/dataset.py
finepipe/deeplearning/model/__init__.py
finepipe/deeplearning/model/model.py
finepipe/deeplearning/model/feed_forward/__init__.py
finepipe/deeplearning/model/feed_forward/feed_forward.py
finepipe/deeplearning/model/gru/__init__.py
finepipe/deeplearning/model/gru/gru.py
finepipe/deeplearning/model/hybrid/__init__.py
finepipe/deeplearning/model/hybrid/hybrid.py
finepipe/deeplearning/model/lstm/__init__.py
finepipe/deeplearning/model/lstm/lstm.py
finepipe/deeplearning/model/resnet1d/__init__.py
finepipe/deeplearning/model/resnet1d/residual1d.py
finepipe/deeplearning/model/resnet1d/resnet1d.py
finepipe-0.0.1.dist-info/METADATA
finepipe-0.0.1.dist-info/WHEEL
finepipe-0.0.1.dist-info/RECORD
